anonweather-0.1.0.dist-info/licenses/LICENSE
theanonweather/__init__.py
theanonweather/fetcher.py
anonweather-0.1.0.dist-info/METADATA
anonweather-0.1.0.dist-info/WHEEL
anonweather-0.1.0.dist-info/top_level.txt
anonweather-0.1.0.dist-info/RECORD
