Metadata-Version: 2.4
Name: anonweather
Version: 0.1.0
Summary: Weather module using api.theanon.xyz API
Home-page: https://api.theanon.xyz
Author: Amit Ranabhat
Author-email: ranabhatamit04@gmail,com
Classifier: Programming Language :: Python :: 3
Classifier: License :: OSI Approved :: MIT License
Requires-Python: >=3.6
License-File: LICENSE
Requires-Dist: requests
Dynamic: author
Dynamic: author-email
Dynamic: classifier
Dynamic: description
Dynamic: description-content-type
Dynamic: home-page
Dynamic: license-file
Dynamic: requires-dist
Dynamic: requires-python
Dynamic: summary
